wundertool/__init__.py
wundertool/cli.py
wundertool/commands.py
wundertool/helpers.py
wundertool/compose/script/run/run.sh
wundertool-0.2.0.dist-info/DESCRIPTION.rst
wundertool-0.2.0.dist-info/METADATA
wundertool-0.2.0.dist-info/RECORD
wundertool-0.2.0.dist-info/WHEEL
wundertool-0.2.0.dist-info/entry_points.txt
wundertool-0.2.0.dist-info/metadata.json
wundertool-0.2.0.dist-info/top_level.txt
