Metadata-Version: 2.0
Name: wundertool
Version: 0.2.0
Summary: Tool for working with Docker containers
Home-page: https://github.com/wunderkraut/wundertool-py
Author: Aleksi Johansson
Author-email: aleksi.johansson@wunderkraut.com
License: MIT
Keywords: wundertools wundertool docker containers container-management
Platform: UNKNOWN
Classifier: Development Status :: 3 - Alpha
Classifier: Intended Audience :: Developers
Classifier: Topic :: Utilities
Classifier: License :: OSI Approved :: MIT License
Classifier: Programming Language :: Python :: 3
Requires-Dist: PyYAML (>=3.11,<4)
Requires-Dist: docker-py (>=1.8.1,<2)
Requires-Dist: fake-factory (>=0.5.7,<1)
Provides-Extra: dev
Requires-Dist: twine; extra == 'dev'
Requires-Dist: wheel; extra == 'dev'
